limepkg_getaccept/.DS_Store
limepkg_getaccept/__init__.py
limepkg_getaccept/common.py
limepkg_getaccept/config/__init__.py
limepkg_getaccept/config/migrations.py
limepkg_getaccept/config/schema.py
limepkg_getaccept/conftest.py
limepkg_getaccept/endpoints/__init__.py
limepkg_getaccept/endpoints/endpoint.py
limepkg_getaccept/endpoints/endpoint_test.py
limepkg_getaccept/endpoints/schemas.py
limepkg_getaccept/getaccept.py
limepkg_getaccept/lime_helpers.py
limepkg_getaccept/types.py
limepkg_getaccept/web_components/.DS_Store
limepkg_getaccept/web_components/__init__.py
limepkg_getaccept/web_components/static/cjs/EnumDocumentStatuses-15b6ee42.js
limepkg_getaccept/web_components/static/cjs/EnumDocumentStatuses-15b6ee42.js.map
limepkg_getaccept/web_components/static/cjs/EnumViews-ea9a87d2.js
limepkg_getaccept/web_components/static/cjs/EnumViews-ea9a87d2.js.map
limepkg_getaccept/web_components/static/cjs/app-globals-3a1e7e63.js
limepkg_getaccept/web_components/static/cjs/app-globals-3a1e7e63.js.map
limepkg_getaccept/web_components/static/cjs/create-email.cjs.entry.js
limepkg_getaccept/web_components/static/cjs/create-email.cjs.entry.js.map
limepkg_getaccept/web_components/static/cjs/custom-fields_4.cjs.entry.js
limepkg_getaccept/web_components/static/cjs/custom-fields_4.cjs.entry.js.map
limepkg_getaccept/web_components/static/cjs/document-error_5.cjs.entry.js
limepkg_getaccept/web_components/static/cjs/document-error_5.cjs.entry.js.map
limepkg_getaccept/web_components/static/cjs/document-list_3.cjs.entry.js
limepkg_getaccept/web_components/static/cjs/document-list_3.cjs.entry.js.map
limepkg_getaccept/web_components/static/cjs/document-page-info.cjs.entry.js
limepkg_getaccept/web_components/static/cjs/document-page-info.cjs.entry.js.map
limepkg_getaccept/web_components/static/cjs/empty-state.cjs.entry.js
limepkg_getaccept/web_components/static/cjs/empty-state.cjs.entry.js.map
limepkg_getaccept/web_components/static/cjs/error-message_14.cjs.entry.js
limepkg_getaccept/web_components/static/collection/components/document-page-info/document-page-info.css
limepkg_getaccept/web_components/static/collection/components/document-page-info/document-page-info.js
limepkg_getaccept/web_components/static/collection/components/document-page-info/document-page-info.js.map
limepkg_getaccept/web_components/static/collection/components/document-page-info/document-page-info.spec.js
limepkg_getaccept/web_components/static/collection/components/document-page-info/document-page-info.spec.js.map
limepkg_getaccept/web_components/static/collection/components/document-validate-info/document-validate-info.css
limepkg_getaccept/web_components/static/collection/components/document-validate-info/document-validate-info.js
limepkg_getaccept/web_components/static/collection/components/document-validate-info/document-validate-info.js.map
limepkg_getaccept/web_components/static/collection/components/document-validate-info/document-validate-info.spec.js
limepkg_getaccept/web_components/static/collection/components/document-validate-info/document-validate-info.spec.js.map
limepkg_getaccept/web_components/static/types/components/document-page-info/document-page-info.d.ts
limepkg_getaccept/web_components/static/types/components/document-validate-info/document-validate-info.d.ts
limepkg_getaccept-1.3.14.dist-info/METADATA
limepkg_getaccept-1.3.14.dist-info/WHEEL
limepkg_getaccept-1.3.14.dist-info/entry_points.txt
limepkg_getaccept-1.3.14.dist-info/RECORD
