Metadata-Version: 2.1
Name: limepkg-getaccept
Version: 1.3.14
Summary: GetAccept eSigning
Author: GetAccept AB
Author-email: integrations@getaccept.com
Requires-Python: >=3.9,<4
Classifier: Programming Language :: Python :: 3
Classifier: Programming Language :: Python :: 3.9
Classifier: Programming Language :: Python :: 3.10
Classifier: Programming Language :: Python :: 3.11
Classifier: Programming Language :: Python :: 3.12
Requires-Dist: bugsnag[flask] (>=4.6.0,<5.0.0)
Requires-Dist: cryptography (>=38.0.1)
Requires-Dist: lime-crm (>=2.40.0,<=4)
